rumdl/__init__.py
rumdl/__main__.py
rumdl/py.typed
rumdl-0.1.8.data/scripts/rumdl
rumdl-0.1.8.dist-info/METADATA
rumdl-0.1.8.dist-info/WHEEL
rumdl-0.1.8.dist-info/licenses/LICENSE
rumdl-0.1.8.dist-info/RECORD
