Metadata-Version: 2.4
Name: rumdl
Version: 0.1.8
Classifier: Development Status :: 4 - Beta
Classifier: Environment :: Console
Classifier: Intended Audience :: Developers
Classifier: License :: OSI Approved :: MIT License
Classifier: Operating System :: OS Independent
Classifier: Programming Language :: Python :: 3
Classifier: Programming Language :: Python :: 3.7
Classifier: Programming Language :: Python :: 3.8
Classifier: Programming Language :: Python :: 3.9
Classifier: Programming Language :: Python :: 3.10
Classifier: Programming Language :: Python :: 3.11
Classifier: Programming Language :: Python :: 3.12
Classifier: Programming Language :: Rust
Classifier: Topic :: Software Development :: Libraries :: Python Modules
Classifier: Topic :: Software Development :: Quality Assurance
Classifier: Topic :: Text Processing :: Markup :: Markdown
License-File: LICENSE
Summary: A fast Markdown linter written in Rust
Home-Page: https://github.com/rvben/rumdl
Author-email: "Ruben J. Jongejan" <ruben.jongejan@gmail.com>
License: MIT
Requires-Python: >=3.7
Project-URL: Homepage, https://github.com/rvben/rumdl
Project-URL: Repository, https://github.com/rvben/rumdl.git
